{
    "userProfile": {
      "id": 1,
      "name": "Marco Rossi",
      "level": "intermediate",
      "isNAI": false,
      "readingLevel": 7,
      "writingLevel": 5,
      "punctuationLevel": 6,
      "badges": [
        {
          "id": "yellow-belt",
          "name": "Cintura Gialla",
          "icon": "🥋🟡",
          "description": "Hai completato 5 esercizi di scrittura!",
          "earnedDate": "2025-02-15T14:30:00.000Z"
        },
        {
          "id": "reader-beginner",
          "name": "Lettore Principiante",
          "icon": "📚",
          "description": "Hai raggiunto l'80% di accuratezza nella lettura!",
          "earnedDate": "2025-02-20T10:15:00.000Z"
        }
      ],
      "points": 350,
      "completedExercises": 14,
      "supportLevel": 100,
      "settings": {
        "notifications": true,
        "soundEffects": true,
        "colorTheme": "default"
      }
    },
    "naiUserProfile": {
      "id": 2,
      "name": "Fatima El Amiri",
      "level": "nai-intermediate",
      "isNAI": true,
      "motherLanguage": "ar",
      "readingLevel": 3,
      "writingLevel": 2,
      "punctuationLevel": 2,
      "badges": [
        {
          "id": "white-belt",
          "name": "Cintura Bianca",
          "icon": "🥋⚪",
          "description": "Hai iniziato il tuo percorso!",
          "earnedDate": "2025-03-01T09:45:00.000Z"
        }
      ],
      "points": 120,
      "completedExercises": 6,
      "supportLevel": 80,
      "settings": {
        "notifications": true,
        "soundEffects": true,
        "colorTheme": "default"
      }
    },
    "userStats": {
      "completedExercises": 14,
      "totalTimeSpent": 320,
      "averageScore": 78,
      "readingLevel": 7,
      "writingLevel": 5,
      "punctuationLevel": 6,
      "registerLevel": 4,
      "readingAccuracy": 84,
      "readingFluency": 76,
      "grammarAccuracy": 72,
      "contentQuality": 81,
      "punctuationAccuracy": 79,
      "registerFlexibility": 68,
      "suggestedExercises": [
        {
          "icon": "✏️",
          "title": "Riscrittura formale",
          "description": "Trasforma un testo informale in un contesto formale",
          "url": "/registri"
        },
        {
          "icon": "📝",
          "title": "Punteggiatura avanzata",
          "description": "Esercizio sui punti e virgola e due punti",
          "url": "/punteggiatura"
        },
        {
          "icon": "🏯",
          "title": "Sfida settimanale",
          "description": "Partecipa alla sfida del Drago d'Oro",
          "url": "/torneo"
        }
      ],
      "skillsProgress": [
        {
          "date": "2025-02-10",
          "reading": 65,
          "writing": 58,
          "punctuation": 60
        },
        {
          "date": "2025-02-17",
          "reading": 72,
          "writing": 62,
          "punctuation": 65
        },
        {
          "date": "2025-02-24",
          "reading": 78,
          "writing": 67,
          "punctuation": 70
        },
        {
          "date": "2025-03-03",
          "reading": 84,
          "writing": 72,
          "punctuation": 79
        }
      ],
      "activityByType": [
        {
          "type": "Lettura",
          "count": 5
        },
        {
          "type": "Scrittura",
          "count": 4
        },
        {
          "type": "Punteggiatura",
          "count": 3
        },
        {
          "type": "Registri",
          "count": 2
        }
      ],
      "errorDistribution": [
        {
          "type": "Grammatica",
          "value": 40
        },
        {
          "type": "Punteggiatura",
          "value": 25
        },
        {
          "type": "Ortografia",
          "value": 20
        },
        {
          "type": "Sintassi",
          "value": 15
        }
      ],
      "tournamentScores": [
        {
          "name": "Settimana 1",
          "score": 65
        },
        {
          "name": "Settimana 2",
          "score": 72
        },
        {
          "name": "Settimana 3",
          "score": 80
        },
        {
          "name": "Settimana 4",
          "score": 85
        }
      ],
      "nextBadges": [
        {
          "icon": "🥋🟠",
          "name": "Cintura Arancione",
          "requirement": "Completa 10 esercizi di scrittura",
          "progress": 60
        },
        {
          "icon": "📖",
          "name": "Lettore Intermedio",
          "requirement": "Raggiungi il 90% di accuratezza nella lettura",
          "progress": 75
        }
      ]
    },
    "recentActivities": [
      {
        "icon": "📖",
        "title": "Lettura Completata",
        "description": "Hai letto 'Il Piccolo Principe' con un'accuratezza dell'84%",
        "timestamp": "2025-03-10T14:30:00.000Z"
      },
      {
        "icon": "✏️",
        "title": "Esercizio di Scrittura",
        "description": "Hai completato la descrizione di un paesaggio",
        "timestamp": "2025-03-09T11:20:00.000Z"
      },
      {
        "icon": "🏅",
        "title": "Badge Guadagnato",
        "description": "Hai ottenuto la Cintura Gialla",
        "timestamp": "2025-03-08T16:45:00.000Z"
      },
      {
        "icon": "🏯",
        "title": "Torneo Lingua Kai",
        "description": "Hai partecipato alla sfida settimanale",
        "timestamp": "2025-03-07T09:15:00.000Z"
      }
    ],
    "readingTexts": {
      "facile": [
        {
          "id": 1,
          "title": "La mia giornata",
          "description": "Un semplice testo sulla routine quotidiana",
          "content": "Ogni mattina mi sveglio alle sette. Faccio colazione con latte e biscotti. Poi vado a scuola. A mezzogiorno pranzo con i miei amici. Nel pomeriggio studio e gioco. La sera ceno con la mia famiglia e guardo un po' di televisione. Vado a letto alle dieci.",
          "audioUrl": "/audio/testo_facile_1.mp3"
        },
        {
          "id": 2,
          "title": "Al parco",
          "description": "Una breve descrizione di un parco cittadino",
          "content": "Il parco è grande e verde. Ci sono molti alberi e fiori colorati. I bambini giocano sul prato. Alcune persone corrono lungo i sentieri. Altre leggono sedute sulle panchine. C'è anche un laghetto con le anatre. In estate fa molto caldo, ma sotto gli alberi si sta freschi.",
          "audioUrl": "/audio/testo_facile_2.mp3"
        }
      ],
      "medio": [
        {
          "id": 3,
          "title": "La leggenda del lago",
          "description": "Una storia tradizionale su un lago misterioso",
          "content": "Molto tempo fa, in un piccolo villaggio di montagna, viveva una giovane ragazza di nome Lucia. Ogni giorno, Lucia andava al lago vicino per raccogliere l'acqua. Una mattina d'inverno, mentre il lago era ghiacciato, vide qualcosa di strano sotto il ghiaccio: una luce brillante che sembrava danzare. Affascinata, si avvicinò per vedere meglio, ma il ghiaccio si ruppe e Lucia cadde nell'acqua gelida. Gli abitanti del villaggio la cercarono per giorni, ma non la trovarono mai. Da allora, nelle notti di luna piena, si dice che si possa vedere una luce danzante sulla superficie del lago, come se Lucia stesse ancora cercando di trovare la via di casa.",
          "audioUrl": "/audio/testo_medio_1.mp3"
        }
      ],
      "difficile": [
        {
          "id": 4,
          "title": "L'importanza della biodiversità",
          "description": "Un testo scientifico sulla biodiversità e l'ecosistema",
          "content": "La biodiversità, ovvero la varietà di forme di vita presenti sulla Terra, è essenziale per il mantenimento degli equilibri ecosistemici e per la sopravvivenza stessa del nostro pianeta. Ogni specie, per quanto insignificante possa sembrare, svolge un ruolo fondamentale nell'ecosistema: gli impollinatori, come api e farfalle, garantiscono la riproduzione delle piante; i decompositori trasformano la materia organica in nutrienti; i predatori regolano le popolazioni di altre specie, evitando sovrappopolamenti dannosi. La perdita di biodiversità, causata principalmente dalla deforestazione, dall'inquinamento e dai cambiamenti climatici, rappresenta una minaccia non solo per l'ambiente, ma anche per la salute e il benessere umano. Proteggere la biodiversità significa salvaguardare le risorse naturali da cui dipendiamo per cibo, medicine e materie prime, oltre a garantire la resilienza degli ecosistemi di fronte ai cambiamenti ambientali.",
          "audioUrl": "/audio/testo_difficile_1.mp3"
        }
      ]
    },
    "writingExercises": {
      "free": [
        {
          "id": 1,
          "title": "Descrivi la tua città",
          "description": "Scrivi un breve testo descrivendo la città in cui vivi o una città che hai visitato",
          "type": "free"
        },
        {
          "id": 2,
          "title": "Il mio film preferito",
          "description": "Racconta la trama del tuo film preferito e spiega perché ti piace",
          "type": "free"
        }
      ],
      "prompt": [
        {
          "id": 3,
          "title": "Una giornata al mare",
          "description": "Descrivi una giornata trascorsa al mare, includendo i dettagli sensoriali (suoni, odori, sensazioni)",
          "type": "prompt",
          "image": "/images/beach.jpg"
        }
      ],
      "rewrite": [
        {
          "id": 4,
          "title": "Riscrittura con sinonimi",
          "description": "Riscrivi il testo sostituendo le parole ripetute con sinonimi appropriati",
          "type": "rewrite",
          "originalText": "Il ragazzo cammina nel parco. Il ragazzo vede un cane. Il cane è grande. Il ragazzo ha paura del cane. Il ragazzo corre via."
        }
      ]
    },
    "punctuationExercises": {
      "facile": [
        {
          "id": 1,
          "title": "Punti e virgole",
          "description": "Inserisci i punti e le virgole nel testo",
          "textWithPunctuation": "Mi chiamo Marco. Ho dodici anni, vivo a Roma e frequento la scuola media. Mi piace giocare a calcio, leggere fumetti e guardare film di avventura. Il mio migliore amico si chiama Luca, anche lui ama il calcio.",
          "textWithoutPunctuation": "Mi chiamo Marco Ho dodici anni vivo a Roma e frequento la scuola media Mi piace giocare a calcio leggere fumetti e guardare film di avventura Il mio migliore amico si chiama Luca anche lui ama il calcio",
          "audioUrl": "/audio/punctuation_1.mp3"
        }
      ],
      "medio": [
        {
          "id": 2,
          "title": "Discorso diretto",
          "description": "Inserisci la punteggiatura corretta nel dialogo",
          "textWithPunctuation": "Paolo chiese: \"Dove stai andando?\"\n\"Vado al cinema,\" rispose Maria, \"vuoi venire anche tu?\"\n\"Mi piacerebbe, ma devo studiare,\" disse Paolo con un sospiro. \"Forse la prossima volta!\"",
          "textWithoutPunctuation": "Paolo chiese Dove stai andando\nVado al cinema rispose Maria vuoi venire anche tu\nMi piacerebbe ma devo studiare disse Paolo con un sospiro Forse la prossima volta",
          "audioUrl": "/audio/punctuation_2.mp3"
        }
      ],
      "difficile": [
        {
          "id": 3,
          "title": "Punteggiatura complessa",
          "description": "Inserisci tutti i segni di punteggiatura appropriati",
          "textWithPunctuation": "L'arte contemporanea — che spesso sfida le convenzioni tradizionali — può essere difficile da comprendere; tuttavia, offre prospettive uniche sulla società moderna. Gli artisti utilizzano vari mezzi espressivi (pittura, scultura, installazioni, video, ecc.) per comunicare le loro idee. \"L'arte non deve essere bella,\" affermava Picasso, \"ma autentica\". Ogni opera, infatti, rappresenta un dialogo tra l'artista e l'osservatore: un dialogo che richiede apertura mentale e sensibilità estetica.",
          "textWithoutPunctuation": "L'arte contemporanea che spesso sfida le convenzioni tradizionali può essere difficile da comprendere tuttavia offre prospettive uniche sulla società moderna Gli artisti utilizzano vari mezzi espressivi pittura scultura installazioni video ecc per comunicare le loro idee L'arte non deve essere bella affermava Picasso ma autentica Ogni opera infatti rappresenta un dialogo tra l'artista e l'osservatore un dialogo che richiede apertura mentale e sensibilità estetica",
          "audioUrl": "/audio/punctuation_3.mp3"
        }
      ]
    },
    "registerExercises": [
      {
        "id": 1,
        "title": "Messaggio formale",
        "description": "Trasforma il messaggio informale in una comunicazione formale",
        "sourceRegister": "informale",
        "targetRegister": "formale",
        "type": "rewrite",
        "originalText": "Ciao prof, scusa ma non posso venire a scuola domani. Ho un po' di febbre e mia mamma dice che è meglio se resto a casa. Mi puoi dire cosa devo studiare per la prossima lezione? Grazie mille, ci vediamo presto!",
        "examples": [
          "Gentile Professore/Professoressa,",
          "La informo che non potrò essere presente alla lezione di domani a causa di uno stato febbrile.",
          "Le porgo i miei più cordiali saluti,"
        ]
      },
      {
        "id": 2,
        "title": "Conversazione informale",
        "description": "Trasforma il testo formale in una conversazione tra amici",
        "sourceRegister": "formale",
        "targetRegister": "informale",
        "type": "rewrite",
        "originalText": "Egregio Signore, con la presente desidero comunicarLe che il prossimo mese sarò lieto di accoglierLa presso la mia residenza estiva per il fine settimana. L'evento inizierà alle ore 18:00 di venerdì 15 luglio e si concluderà domenica 17 luglio. La prego di confermare la Sua partecipazione entro il 30 giugno. In attesa di un Suo gentile riscontro, Le porgo i miei più cordiali saluti.",
        "examples": [
          "Ehi! Ti va di venire a casa mia al mare?",
          "Dai, sarà super divertente!",
          "Fammi sapere se vieni, così mi organizzo!"
        ]
      }
    ],
    "challengeTournament": {
      "challenges": [
        {
          "id": 1,
          "title": "Sfida della Tigre",
          "description": "Metti alla prova le tue conoscenze grammaticali",
          "icon": "🐯",
          "difficulty": "intermedio",
          "questionCount": 10
        },
        {
          "id": 2,
          "title": "Sfida del Drago",
          "description": "Sfida di comprensione del testo e vocabolario",
          "icon": "🐲",
          "difficulty": "avanzato",
          "questionCount": 15
        }
      ],
      "weeklyChallenge": {
        "id": 3,
        "title": "Sfida del Drago d'Oro",
        "description": "La sfida speciale della settimana con punti bonus!",
        "icon": "🐉",
        "difficulty": "intermedio",
        "questionCount": 12
      },
      "opponents": [
        {
          "id": 1,
          "name": "Giulia",
          "avatar": "👧",
          "level": "intermedio",
          "wins": 12
        },
        {
          "id": 2,
          "name": "Alessandro",
          "avatar": "👦",
          "level": "base",
          "wins": 8
        },
        {
          "id": 3,
          "name": "Sofia",
          "avatar": "👩",
          "level": "avanzato",
          "wins": 18
        }
      ]
    },
    "dojoLeaderboard": [
      {
        "id": 1,
        "name": "Sofia",
        "avatar": "👩",
        "helpPoints": 175,
        "badge": "🥇 Maestro del Dojo"
      },
      {
        "id": 2,
        "name": "Luca",
        "avatar": "👨",
        "helpPoints": 130,
        "badge": "🥈 Mentor Senior"
      },
      {
        "id": 3,
        "name": "Giorgia",
        "avatar": "👧",
        "helpPoints": 95,
        "badge": "🥉 Tutor"
      },
      {
        "id": 4,
        "name": "Marco",
        "avatar": "👦",
        "helpPoints": 65,
        "badge": "⭐ Assistente"
      }
    ],
    "helpRequests": [
      {
        "id": 1,
        "title": "Aiuto con i verbi irregolari",
        "description": "Non riesco a capire come si coniugano i verbi irregolari al passato remoto",
        "subject": "grammar",
        "status": "open",
        "user": {
          "name": "Alessio",
          "avatar": "👦"
        }
      },
      {
        "id": 2,
        "title": "Problemi con l'uso della virgola",
        "description": "Non sono sicura di quando usare la virgola nelle frasi complesse",
        "subject": "punctuation",
        "status": "open",
        "user": {
          "name": "Chiara",
          "avatar": "👧"
        }
      }
    ],
    "glossary": {
      "ar": [
        {
          "id": 1,
          "italian": "casa",
          "translation": "منزل",
          "examples": [
            {
              "italian": "Vado a casa",
              "translation": "أنا ذاهب إلى المنزل"
            }
          ]
        },
        {
          "id": 2,
          "italian": "scuola",
          "translation": "مدرسة",
          "examples": [
            {
              "italian": "La scuola è chiusa",
              "translation": "المدرسة مغلقة"
            }
          ]
        }
      ],
      "zh": [
        {
          "id": 3,
          "italian": "casa",
          "translation": "家",
          "examples": [
            {
              "italian": "Vado a casa",
              "translation": "我回家"
            }
          ]
        },
        {
          "id": 4,
          "italian": "scuola",
          "translation": "学校",
          "examples": [
            {
              "italian": "La scuola è chiusa",
              "translation": "学校关闭了"
            }
          ]
        }
      ]
    },
    "recentTranslations": {
      "ar": [
        {
          "original": "Devi completare l'esercizio entro domani",
          "translation": "يجب عليك إكمال التمرين بحلول الغد",
          "timestamp": "2025-03-10T10:30:00.000Z"
        },
        {
          "original": "Quale libro stai leggendo?",
          "translation": "أي كتاب تقرأ؟",
          "timestamp": "2025-03-09T14:45:00.000Z"
        }
      ],
      "zh": [
        {
          "original": "Devi completare l'esercizio entro domani",
          "translation": "你必须在明天前完成练习",
          "timestamp": "2025-03-10T10:30:00.000Z"
        },
        {
          "original": "Quale libro stai leggendo?",
          "translation": "你在读什么书？",
          "timestamp": "2025-03-09T14:45:00.000Z"
        }
      ]
    }
  }